{
    "linux_version": "6.9.1",
    "bc_dir": "linux-6.9.1-bc",
    "ll_dir": "linux-6.9.1-ll",
    "txt_dir": "passes-out",
    "file_count": 23804,
    "scuaf_gadgets": 1030,
    "lock_func_counts": {
        "total": 482,
        "nesting_level": {
            "0": 481,
            "1": 1
        },
        "types": {
            "_raw_write_lock_irqsave": 1,
            "_raw_read_lock": 1,
            "down_read": 3,
            "mutex_lock_nested": 387,
            "_raw_spin_lock_irqsave": 18,
            "down_write": 49,
            "down_trylock": 1,
            "_raw_spin_lock_bh": 4,
            "_raw_spin_lock": 4,
            "mutex_lock_killable_nested": 4,
            "mutex_lock_interruptible_nested": 9,
            "_raw_write_lock_irq": 1
        },
        "spin_lock": {
            "total": 26,
            "nesting_level": {
                "0": 26
            },
            "types": {
                "_raw_spin_lock_irqsave": 18,
                "_raw_spin_lock_bh": 4,
                "_raw_spin_lock": 4
            }
        },
        "spin_trylock": {
            "total": 0,
            "nesting_level": {},
            "types": {}
        },
        "read_lock": {
            "total": 1,
            "nesting_level": {
                "0": 1
            },
            "types": {
                "_raw_read_lock": 1
            }
        },
        "read_trylock": {
            "total": 0,
            "nesting_level": {},
            "types": {}
        },
        "write_lock": {
            "total": 2,
            "nesting_level": {
                "0": 1,
                "1": 1
            },
            "types": {
                "_raw_write_lock_irqsave": 1,
                "_raw_write_lock_irq": 1
            }
        },
        "write_trylock": {
            "total": 0,
            "nesting_level": {},
            "types": {}
        },
        "down_read": {
            "total": 3,
            "nesting_level": {
                "0": 3
            },
            "types": {
                "down_read": 3
            }
        },
        "down_write": {
            "total": 49,
            "nesting_level": {
                "0": 49
            },
            "types": {
                "down_write": 49
            }
        },
        "mutex_lock": {
            "total": 400,
            "nesting_level": {
                "0": 400
            },
            "types": {
                "mutex_lock_nested": 387,
                "mutex_lock_killable_nested": 4,
                "mutex_lock_interruptible_nested": 9
            }
        },
        "mutex_trylock": {
            "total": 0,
            "nesting_level": {},
            "types": {}
        },
        "down": {
            "total": 1,
            "nesting_level": {
                "0": 1
            },
            "types": {
                "down_trylock": 1
            }
        },
        "mutex_count": {
            "total": 400,
            "nesting_level": {
                "0": 400
            }
        },
        "spin_lock_count": {
            "total": 26,
            "nesting_level": {
                "0": 26
            }
        },
        "rw_spin_lock_count": {
            "total": 3,
            "nesting_level": {
                "0": 2,
                "1": 1
            }
        },
        "semaphore_count": {
            "total": 1,
            "nesting_level": {
                "0": 1
            }
        },
        "rw_semaphore_count": {
            "total": 52,
            "nesting_level": {
                "0": 52
            }
        }
    },
    "unlock_func_counts": {
        "total": 482,
        "nesting_level": {
            "0": 482
        },
        "types": {
            "_raw_write_unlock_irqrestore": 1,
            "_raw_read_unlock": 1,
            "up_read": 4,
            "mutex_unlock": 400,
            "_raw_spin_unlock_irqrestore": 17,
            "up_write": 48,
            "up": 2,
            "_raw_spin_unlock_bh": 4,
            "_raw_spin_unlock": 4,
            "_raw_write_unlock_irq": 1
        },
        "spin_unlock": {
            "total": 25,
            "nesting_level": {
                "0": 25
            },
            "types": {
                "_raw_spin_unlock_irqrestore": 17,
                "_raw_spin_unlock_bh": 4,
                "_raw_spin_unlock": 4
            }
        },
        "read_unlock": {
            "total": 1,
            "nesting_level": {
                "0": 1
            },
            "types": {
                "_raw_read_unlock": 1
            }
        },
        "write_unlock": {
            "total": 2,
            "nesting_level": {
                "0": 2
            },
            "types": {
                "_raw_write_unlock_irqrestore": 1,
                "_raw_write_unlock_irq": 1
            }
        },
        "up_read": {
            "total": 4,
            "nesting_level": {
                "0": 4
            },
            "types": {
                "up_read": 4
            }
        },
        "up_write": {
            "total": 48,
            "nesting_level": {
                "0": 48
            },
            "types": {
                "up_write": 48
            }
        },
        "mutex_unlock": {
            "total": 400,
            "nesting_level": {
                "0": 400
            },
            "types": {
                "mutex_unlock": 400
            }
        },
        "up": {
            "total": 2,
            "nesting_level": {
                "0": 2
            },
            "types": {
                "up": 2
            }
        }
    },
    "free_gadgets": {
        "total": 1816,
        "nesting_level": {
            "1": 500,
            "0": 1316
        },
        "types": {
            "guarded_free": 1626,
            "guarded_free_val": 146,
            "guarded_free_null": 44
        },
        "guarded_free": {
            "total": 1626,
            "nesting_level": {
                "1": 400,
                "0": 1226
            },
            "types": {
                "guarded_free": 1626
            }
        },
        "guarded_free_null": {
            "total": 44,
            "nesting_level": {
                "1": 44
            },
            "types": {
                "guarded_free_null": 44
            }
        },
        "guarded_free_val": {
            "total": 146,
            "nesting_level": {
                "1": 56,
                "0": 90
            },
            "types": {
                "guarded_free_val": 146
            }
        },
        "guarded_free_list_del": {
            "total": 0,
            "nesting_level": {},
            "types": {}
        }
    },
    "use_gadgets": {
        "total": 2464,
        "nesting_level": {
            "0": 1965,
            "1": 437,
            "2": 62
        },
        "types": {
            "fptr_copy": 1054,
            "fptr_call": 1410
        },
        "fptr_copy": {
            "total": 1054,
            "nesting_level": {
                "0": 718,
                "1": 274,
                "2": 62
            },
            "types": {
                "fptr_copy": 1054
            }
        },
        "fptr_call": {
            "total": 1410,
            "nesting_level": {
                "0": 1247,
                "1": 163
            },
            "types": {
                "fptr_call": 1410
            }
        }
    }
}